compose_tags/__init__.py
compose_tags/apps.py
compose_tags/node.py
compose_tags/tag.py
compose_tags/templatetags/__init__.py
compose_tags/templatetags/compose.py
django_compose_tags-0.0.2.dist-info/LICENSE.md
django_compose_tags-0.0.2.dist-info/METADATA
django_compose_tags-0.0.2.dist-info/WHEEL
django_compose_tags-0.0.2.dist-info/top_level.txt
django_compose_tags-0.0.2.dist-info/RECORD
